{
    "players": [
        {
            "id": 8465166,
            "name": "Craig Adams"
        },
        {
            "id": 8469779,
            "name": "Keith Aucoin"
        },
        {
            "id": 8468560,
            "name": "Ryan Bayda"
        },
        {
            "id": 8445735,
            "name": "Rod Brind'Amour"
        },
        {
            "id": 8469044,
            "name": "Wade Brookbank"
        },
        {
            "id": 8467396,
            "name": "Erik Cole"
        },
        {
            "id": 8470101,
            "name": "Tim Conboy"
        },
        {
            "id": 8464989,
            "name": "Matt Cullen"
        },
        {
            "id": 8470622,
            "name": "Patrick Eaves"
        },
        {
            "id": 8470373,
            "name": "Jeff Hamilton"
        },
        {
            "id": 8470821,
            "name": "Joe Jensen"
        },
        {
            "id": 8471217,
            "name": "Andrew Ladd"
        },
        {
            "id": 8469812,
            "name": "Chad LaRose"
        },
        {
            "id": 8465189,
            "name": "Trevor Letowski"
        },
        {
            "id": 8469522,
            "name": "Brandon Nolan"
        },
        {
            "id": 8469462,
            "name": "Tuomo Ruutu"
        },
        {
            "id": 8466035,
            "name": "Sergei Samsonov"
        },
        {
            "id": 8470595,
            "name": "Eric Staal"
        },
        {
            "id": 8458943,
            "name": "Cory Stillman"
        },
        {
            "id": 8459547,
            "name": "Scott Walker"
        },
        {
            "id": 8458537,
            "name": "Ray Whitney"
        },
        {
            "id": 8468508,
            "name": "Justin Williams"
        },
        {
            "id": 8471282,
            "name": "Casey Borer"
        },
        {
            "id": 8467915,
            "name": "Mike Commodore"
        },
        {
            "id": 8466215,
            "name": "Joe Corvo"
        },
        {
            "id": 8469476,
            "name": "Tim Gleason"
        },
        {
            "id": 8456547,
            "name": "Bret Hedican"
        },
        {
            "id": 8467949,
            "name": "Frantisek Kaberle"
        },
        {
            "id": 8470208,
            "name": "Joey Mormina"
        },
        {
            "id": 8469619,
            "name": "Dennis Seidenberg"
        },
        {
            "id": 8467889,
            "name": "David Tanabe"
        },
        {
            "id": 8468577,
            "name": "Niclas Wallin"
        },
        {
            "id": 8452371,
            "name": "Glen Wesley"
        },
        {
            "id": 8460715,
            "name": "John Grahame"
        },
        {
            "id": 8468038,
            "name": "Michael Leighton"
        },
        {
            "id": 8470320,
            "name": "Cam Ward"
        }
    ]
}