{
    "players": [
        {
            "id": 8469474,
            "name": "Colby Armstrong"
        },
        {
            "id": 8467880,
            "name": "Kris Beech"
        },
        {
            "id": 8470283,
            "name": "Tim Brent"
        },
        {
            "id": 8470299,
            "name": "Erik Christensen"
        },
        {
            "id": 8471675,
            "name": "Sidney Crosby"
        },
        {
            "id": 8466393,
            "name": "Pascal Dupuis"
        },
        {
            "id": 8470663,
            "name": "Jonathan Filewich"
        },
        {
            "id": 8467925,
            "name": "Adam Hall"
        },
        {
            "id": 8466148,
            "name": "Marian Hossa"
        },
        {
            "id": 8470295,
            "name": "Connor James"
        },
        {
            "id": 8471311,
            "name": "Tyler Kennedy"
        },
        {
            "id": 8462060,
            "name": "Georges Laraque"
        },
        {
            "id": 8471215,
            "name": "Evgeni Malkin"
        },
        {
            "id": 8467988,
            "name": "Ryan Malone"
        },
        {
            "id": 8470383,
            "name": "Chris Minard"
        },
        {
            "id": 8450725,
            "name": "Mark Recchi"
        },
        {
            "id": 8450900,
            "name": "Gary Roberts"
        },
        {
            "id": 8467393,
            "name": "Jarkko Ruutu"
        },
        {
            "id": 8468503,
            "name": "Nathan Smith"
        },
        {
            "id": 8473533,
            "name": "Jordan Staal"
        },
        {
            "id": 8470625,
            "name": "Ryan Stone"
        },
        {
            "id": 8460465,
            "name": "Petr Sykora"
        },
        {
            "id": 8468510,
            "name": "Jeff Taffe"
        },
        {
            "id": 8470171,
            "name": "Max Talbot"
        },
        {
            "id": 8467580,
            "name": "Mark Eaton"
        },
        {
            "id": 8459628,
            "name": "Hal Gill"
        },
        {
            "id": 8471274,
            "name": "Alex Goligoski"
        },
        {
            "id": 8458951,
            "name": "Sergei Gonchar"
        },
        {
            "id": 8471724,
            "name": "Kris Letang"
        },
        {
            "id": 8459558,
            "name": "Alain Nasreddine"
        },
        {
            "id": 8468498,
            "name": "Brooks Orpik"
        },
        {
            "id": 8467452,
            "name": "Rob Scuderi"
        },
        {
            "id": 8458172,
            "name": "Darryl Sydor"
        },
        {
            "id": 8470309,
            "name": "Ryan Whitney"
        },
        {
            "id": 8469152,
            "name": "Ty Conklin"
        },
        {
            "id": 8470594,
            "name": "Marc-Andre Fleury"
        },
        {
            "id": 8467430,
            "name": "Dany Sabourin"
        }
    ]
}