{
    "players": [
        {
            "id": 8476857,
            "name": "Pontus Aberg"
        },
        {
            "id": 8479465,
            "name": "Drake Caggiula"
        },
        {
            "id": 8469500,
            "name": "Michael Cammalleri"
        },
        {
            "id": 8477934,
            "name": "Leon Draisaitl"
        },
        {
            "id": 8469638,
            "name": "Jussi Jokinen"
        },
        {
            "id": 8475178,
            "name": "Zack Kassian"
        },
        {
            "id": 8476915,
            "name": "Jujhar Khaira"
        },
        {
            "id": 8473914,
            "name": "Mark Letestu"
        },
        {
            "id": 8473473,
            "name": "Milan Lucic"
        },
        {
            "id": 8474089,
            "name": "Brad Malone"
        },
        {
            "id": 8474034,
            "name": "Patrick Maroon"
        },
        {
            "id": 8478402,
            "name": "Connor McDavid"
        },
        {
            "id": 8476454,
            "name": "Ryan Nugent-Hopkins"
        },
        {
            "id": 8476336,
            "name": "Iiro Pakarinen"
        },
        {
            "id": 8479344,
            "name": "Jesse Puljujarvi"
        },
        {
            "id": 8476427,
            "name": "Ty Rattie"
        },
        {
            "id": 8477415,
            "name": "Anton Slepyshev"
        },
        {
            "id": 8476458,
            "name": "Ryan Strome"
        },
        {
            "id": 8477573,
            "name": "Nathan Walker"
        },
        {
            "id": 8479977,
            "name": "Kailer Yamamoto"
        },
        {
            "id": 8479483,
            "name": "Yohann Auvitu"
        },
        {
            "id": 8478451,
            "name": "Ethan Bear"
        },
        {
            "id": 8476988,
            "name": "Matt Benning"
        },
        {
            "id": 8475869,
            "name": "Brandon Davidson"
        },
        {
            "id": 8473468,
            "name": "Eric Gryba"
        },
        {
            "id": 8476472,
            "name": "Oscar Klefbom"
        },
        {
            "id": 8476457,
            "name": "Adam Larsson"
        },
        {
            "id": 8476397,
            "name": "Keegan Lowe"
        },
        {
            "id": 8477498,
            "name": "Darnell Nurse"
        },
        {
            "id": 8471729,
            "name": "Kris Russell"
        },
        {
            "id": 8471284,
            "name": "Andrej Sekera"
        },
        {
            "id": 8476316,
            "name": "Laurent Brossoit"
        },
        {
            "id": 8471219,
            "name": "Al Montoya"
        },
        {
            "id": 8475660,
            "name": "Cam Talbot"
        }
    ]
}