{
    "players": [
        {
            "id": 8471326,
            "name": "Patrick Bordeleau"
        },
        {
            "id": 8474008,
            "name": "Paul Carey"
        },
        {
            "id": 8471718,
            "name": "Marc-Andre Cliche"
        },
        {
            "id": 8471703,
            "name": "Steve Downie"
        },
        {
            "id": 8475168,
            "name": "Matt Duchene"
        },
        {
            "id": 8475767,
            "name": "Joey Hishon"
        },
        {
            "id": 8476455,
            "name": "Gabriel Landeskog"
        },
        {
            "id": 8477492,
            "name": "Nathan MacKinnon"
        },
        {
            "id": 8474089,
            "name": "Brad Malone"
        },
        {
            "id": 8473465,
            "name": "Jamie McGinn"
        },
        {
            "id": 8471657,
            "name": "Cody McLeod"
        },
        {
            "id": 8470750,
            "name": "John Mitchell"
        },
        {
            "id": 8475158,
            "name": "Ryan O'Reilly"
        },
        {
            "id": 8469707,
            "name": "PA Parenteau"
        },
        {
            "id": 8471669,
            "name": "Paul Stastny"
        },
        {
            "id": 8470171,
            "name": "Max Talbot"
        },
        {
            "id": 8467338,
            "name": "Alex Tanguay"
        },
        {
            "id": 8470189,
            "name": "David Van Der Gulik"
        },
        {
            "id": 8475197,
            "name": "Tyson Barrie"
        },
        {
            "id": 8470378,
            "name": "Andre Benoit"
        },
        {
            "id": 8475206,
            "name": "Stefan Elliott"
        },
        {
            "id": 8470317,
            "name": "Nate Guenin"
        },
        {
            "id": 8470699,
            "name": "Jan Hejda"
        },
        {
            "id": 8474207,
            "name": "Nick Holden"
        },
        {
            "id": 8471436,
            "name": "Matt Hunwick"
        },
        {
            "id": 8473446,
            "name": "Erik Johnson"
        },
        {
            "id": 8464981,
            "name": "Cory Sarich"
        },
        {
            "id": 8476798,
            "name": "Karl Stollery"
        },
        {
            "id": 8473700,
            "name": "Ryan Wilson"
        },
        {
            "id": 8475824,
            "name": "Sami Aittokallio"
        },
        {
            "id": 8473499,
            "name": "Reto Berra"
        },
        {
            "id": 8462044,
            "name": "Jean-Sebastien Giguere"
        },
        {
            "id": 8473575,
            "name": "Semyon Varlamov"
        }
    ]
}