{
    "players": [
        {
            "id": 8446003,
            "name": "Andrew Cassels"
        },
        {
            "id": 8446163,
            "name": "Yvon Corriveau"
        },
        {
            "id": 8446217,
            "name": "Murray Craven"
        },
        {
            "id": 8446251,
            "name": "John Cullen"
        },
        {
            "id": 8446261,
            "name": "Randy Cunneyworth"
        },
        {
            "id": 8456009,
            "name": "Scott Daniels"
        },
        {
            "id": 8456023,
            "name": "Joseph Day"
        },
        {
            "id": 8447192,
            "name": "Paul Gillis"
        },
        {
            "id": 8447313,
            "name": "Christopher Govedaris"
        },
        {
            "id": 8447383,
            "name": "Mark Greig"
        },
        {
            "id": 8448225,
            "name": "Mark Janssens"
        },
        {
            "id": 8448471,
            "name": "Tim Kerr"
        },
        {
            "id": 8448542,
            "name": "Robert Kron"
        },
        {
            "id": 8448539,
            "name": "Nick Kypreos"
        },
        {
            "id": 8448771,
            "name": "Jamie Leach"
        },
        {
            "id": 8449477,
            "name": "Jim McKenzie"
        },
        {
            "id": 8458821,
            "name": "Barry Nieckar"
        },
        {
            "id": 8458573,
            "name": "Michael Nylander"
        },
        {
            "id": 8458946,
            "name": "Robert Petrovicky"
        },
        {
            "id": 8458523,
            "name": "Patrick Poulin"
        },
        {
            "id": 8457921,
            "name": "Geoff Sanderson"
        },
        {
            "id": 8452216,
            "name": "Pat Verbeek"
        },
        {
            "id": 8452557,
            "name": "Terry Yake"
        },
        {
            "id": 8444893,
            "name": "Jim Agnew"
        },
        {
            "id": 8445783,
            "name": "Adam Burt"
        },
        {
            "id": 8447981,
            "name": "Doug Houda"
        },
        {
            "id": 8448419,
            "name": "Dan Keczmer"
        },
        {
            "id": 8448521,
            "name": "Steve Konroyd"
        },
        {
            "id": 8448616,
            "name": "Randy Ladouceur"
        },
        {
            "id": 8450270,
            "name": "Allen Pedersen"
        },
        {
            "id": 8452353,
            "name": "Eric Weinrich"
        },
        {
            "id": 8452584,
            "name": "Zarley Zalapski"
        },
        {
            "id": 8445769,
            "name": "Sean Burke"
        },
        {
            "id": 8455996,
            "name": "Corrie D'alessio"
        },
        {
            "id": 8447303,
            "name": "Mario Gosselin"
        },
        {
            "id": 8457049,
            "name": "Mike Lenarduzzi"
        },
        {
            "id": 8450390,
            "name": "Frank Pietrangelo"
        }
    ]
}