{
    "players": [
        {
            "id": 8444898,
            "name": "Greg Adams"
        },
        {
            "id": 8444913,
            "name": "Ray Allison"
        },
        {
            "id": 8445252,
            "name": "Bill Barber"
        },
        {
            "id": 8445685,
            "name": "Mel Bridgman"
        },
        {
            "id": 8446007,
            "name": "Lindsay Carson"
        },
        {
            "id": 8446098,
            "name": "Bobby Clarke"
        },
        {
            "id": 8446869,
            "name": "Ron Flockhart"
        },
        {
            "id": 8447302,
            "name": "Tom Gorence"
        },
        {
            "id": 8447819,
            "name": "Al Hill"
        },
        {
            "id": 8447934,
            "name": "Paul Holmgren"
        },
        {
            "id": 8448471,
            "name": "Tim Kerr"
        },
        {
            "id": 8448729,
            "name": "Reggie Leach"
        },
        {
            "id": 8448857,
            "name": "Ken Linseman"
        },
        {
            "id": 8449583,
            "name": "David Michayluk"
        },
        {
            "id": 8449704,
            "name": "Gary Morrison"
        },
        {
            "id": 8450595,
            "name": "Brian Propp"
        },
        {
            "id": 8451383,
            "name": "Ilkka Sinisalo"
        },
        {
            "id": 8451386,
            "name": "Darryl Sittler"
        },
        {
            "id": 8451867,
            "name": "Mark Taylor"
        },
        {
            "id": 8452461,
            "name": "Gord Williams"
        },
        {
            "id": 8445090,
            "name": "Fred Arthur"
        },
        {
            "id": 8445211,
            "name": "Reid Bailey"
        },
        {
            "id": 8445298,
            "name": "Frank Bathe"
        },
        {
            "id": 8445626,
            "name": "Mark Botell"
        },
        {
            "id": 8446111,
            "name": "Glen Cochrane"
        },
        {
            "id": 8446291,
            "name": "Bob Dailey"
        },
        {
            "id": 8446711,
            "name": "Thomas Eriksson"
        },
        {
            "id": 8447918,
            "name": "Bob Hoffmeyer"
        },
        {
            "id": 8449175,
            "name": "Brad Marsh"
        },
        {
            "id": 8451559,
            "name": "Steven Smith"
        },
        {
            "id": 8452319,
            "name": "Jimmy Watson"
        },
        {
            "id": 8452492,
            "name": "Behn Wilson"
        },
        {
            "id": 8448853,
            "name": "Pelle Lindbergh"
        },
        {
            "id": 8450343,
            "name": "Pete Peeters"
        },
        {
            "id": 8451626,
            "name": "Rick St. Croix"
        }
    ]
}