{
    "players": [
        {
            "id": 8476062,
            "name": "Mark Arcobello"
        },
        {
            "id": 8478042,
            "name": "Viktor Arvidsson"
        },
        {
            "id": 8475192,
            "name": "Taylor Beck"
        },
        {
            "id": 8475268,
            "name": "Gabriel Bourque"
        },
        {
            "id": 8471733,
            "name": "Rich Clune"
        },
        {
            "id": 8464989,
            "name": "Matt Cullen"
        },
        {
            "id": 8477942,
            "name": "Kevin Fiala"
        },
        {
            "id": 8467370,
            "name": "Mike Fisher"
        },
        {
            "id": 8476887,
            "name": "Filip Forsberg"
        },
        {
            "id": 8468700,
            "name": "Paul Gaustad"
        },
        {
            "id": 8475714,
            "name": "Calle Jarnkrok"
        },
        {
            "id": 8466140,
            "name": "Olli Jokinen"
        },
        {
            "id": 8471707,
            "name": "James Neal"
        },
        {
            "id": 8470180,
            "name": "Eric Nystrom"
        },
        {
            "id": 8467371,
            "name": "Mike Ribeiro"
        },
        {
            "id": 8469485,
            "name": "Derek Roy"
        },
        {
            "id": 8476447,
            "name": "Miikka Salomaki"
        },
        {
            "id": 8471390,
            "name": "Mike Santorelli"
        },
        {
            "id": 8475225,
            "name": "Craig Smith"
        },
        {
            "id": 8473537,
            "name": "Viktor Stalberg"
        },
        {
            "id": 8474569,
            "name": "Colin Wilson"
        },
        {
            "id": 8473658,
            "name": "Victor Bartley"
        },
        {
            "id": 8475868,
            "name": "Anthony Bitetto"
        },
        {
            "id": 8475218,
            "name": "Mattias Ekholm"
        },
        {
            "id": 8475176,
            "name": "Ryan Ellis"
        },
        {
            "id": 8471742,
            "name": "Cody Franson"
        },
        {
            "id": 8477495,
            "name": "Seth Jones"
        },
        {
            "id": 8474600,
            "name": "Roman Josi"
        },
        {
            "id": 8473921,
            "name": "Joe Piskula"
        },
        {
            "id": 8468501,
            "name": "Anton Volchenkov"
        },
        {
            "id": 8470642,
            "name": "Shea Weber"
        },
        {
            "id": 8475622,
            "name": "Carter Hutton"
        },
        {
            "id": 8476992,
            "name": "Marek Mazanec"
        },
        {
            "id": 8471469,
            "name": "Pekka Rinne"
        }
    ]
}