{
    "players": [
        {
            "id": 8467880,
            "name": "Kris Beech"
        },
        {
            "id": 8459450,
            "name": "Shean Donovan"
        },
        {
            "id": 8468532,
            "name": "Shane Endicott"
        },
        {
            "id": 8462159,
            "name": "Jan Hrdina"
        },
        {
            "id": 8466398,
            "name": "Tom Kostopoulos"
        },
        {
            "id": 8458529,
            "name": "Alex Kovalev"
        },
        {
            "id": 8467347,
            "name": "Milan Kraft"
        },
        {
            "id": 8464983,
            "name": "Dan Lacouture"
        },
        {
            "id": 8456966,
            "name": "Robert Lang"
        },
        {
            "id": 8448782,
            "name": "Mario Lemieux"
        },
        {
            "id": 8457203,
            "name": "Kent Manderville"
        },
        {
            "id": 8465220,
            "name": "Eric Meloche"
        },
        {
            "id": 8462054,
            "name": "Aleksey Morozov"
        },
        {
            "id": 8466210,
            "name": "Ville Nieminen"
        },
        {
            "id": 8459486,
            "name": "Krzysztof Oliwa"
        },
        {
            "id": 8467543,
            "name": "Toby Petersen"
        },
        {
            "id": 8460507,
            "name": "Wayne Primeau"
        },
        {
            "id": 8450825,
            "name": "Stephane Richer"
        },
        {
            "id": 8466110,
            "name": "Randy Robitaille"
        },
        {
            "id": 8451711,
            "name": "Kevin Stevens"
        },
        {
            "id": 8458955,
            "name": "Martin Straka"
        },
        {
            "id": 8468438,
            "name": "Billy Tibbetts"
        },
        {
            "id": 8459146,
            "name": "Jeff Toms"
        },
        {
            "id": 8466189,
            "name": "Rick Berry"
        },
        {
            "id": 8466333,
            "name": "Andrew Ference"
        },
        {
            "id": 8459522,
            "name": "John Jakopin"
        },
        {
            "id": 8459700,
            "name": "Hans Jonsson"
        },
        {
            "id": 8458942,
            "name": "Darius Kasparaitis"
        },
        {
            "id": 8458805,
            "name": "Janne Laukkanen"
        },
        {
            "id": 8466203,
            "name": "Josef Melichar"
        },
        {
            "id": 8457421,
            "name": "Ian Moran"
        },
        {
            "id": 8458546,
            "name": "Jamie Pushor"
        },
        {
            "id": 8465058,
            "name": "Michal Rozsival"
        },
        {
            "id": 8459448,
            "name": "Mike Wilson"
        },
        {
            "id": 8462102,
            "name": "Jean-Sebastien Aubin"
        },
        {
            "id": 8460704,
            "name": "Johan Hedberg"
        }
    ]
}