{
    "players": [
        {
            "id": 8455429,
            "name": "Tony Amonte"
        },
        {
            "id": 8446217,
            "name": "Murray Craven"
        },
        {
            "id": 8455984,
            "name": "Jim Cummins"
        },
        {
            "id": 8459515,
            "name": "Eric Daze"
        },
        {
            "id": 8456121,
            "name": "Steve Dubinsky"
        },
        {
            "id": 8456349,
            "name": "Daniel Gauthier"
        },
        {
            "id": 8447345,
            "name": "Dirk Graham"
        },
        {
            "id": 8456441,
            "name": "Brent Grieve"
        },
        {
            "id": 8447963,
            "name": "Tony Horacek"
        },
        {
            "id": 8448483,
            "name": "Darin Kimble"
        },
        {
            "id": 8458949,
            "name": "Sergei Krivokrasov"
        },
        {
            "id": 8449751,
            "name": "Joe Murphy"
        },
        {
            "id": 8449881,
            "name": "Bernie Nicholls"
        },
        {
            "id": 8458523,
            "name": "Patrick Poulin"
        },
        {
            "id": 8450978,
            "name": "Jeremy Roenick"
        },
        {
            "id": 8451080,
            "name": "Christian Ruuttu"
        },
        {
            "id": 8451146,
            "name": "Denis Savard"
        },
        {
            "id": 8458972,
            "name": "Jeff Shantz"
        },
        {
            "id": 8451794,
            "name": "Brent Sutter"
        },
        {
            "id": 8451791,
            "name": "Rich Sutter"
        },
        {
            "id": 8452571,
            "name": "Paul Ysebaert"
        },
        {
            "id": 8455805,
            "name": "Keith Carney"
        },
        {
            "id": 8446053,
            "name": "Chris Chelios"
        },
        {
            "id": 8446417,
            "name": "Gerald Diduck"
        },
        {
            "id": 8448292,
            "name": "Roger Johansson"
        },
        {
            "id": 8451073,
            "name": "Cam Russell"
        },
        {
            "id": 8451558,
            "name": "Steve Smith"
        },
        {
            "id": 8451570,
            "name": "Greg Smyth"
        },
        {
            "id": 8451804,
            "name": "Gary Suter"
        },
        {
            "id": 8452353,
            "name": "Eric Weinrich"
        },
        {
            "id": 8445386,
            "name": "Ed Belfour"
        },
        {
            "id": 8447449,
            "name": "Jeff Hackett"
        },
        {
            "id": 8452246,
            "name": "Jimmy Waite"
        }
    ]
}