{
    "players": [
        {
            "id": 8474150,
            "name": "Mikael Backlund"
        },
        {
            "id": 8477935,
            "name": "Sam Bennett"
        },
        {
            "id": 8479346,
            "name": "Dillon Dube"
        },
        {
            "id": 8475278,
            "name": "Byron Froese"
        },
        {
            "id": 8476346,
            "name": "Johnny Gaudreau"
        },
        {
            "id": 8478446,
            "name": "Glenn Gawdin"
        },
        {
            "id": 8476410,
            "name": "Josh Leivo"
        },
        {
            "id": 8477496,
            "name": "Elias Lindholm"
        },
        {
            "id": 8473473,
            "name": "Milan Lucic"
        },
        {
            "id": 8478233,
            "name": "Andrew Mangiapane"
        },
        {
            "id": 8477497,
            "name": "Sean Monahan"
        },
        {
            "id": 8475807,
            "name": "Joakim Nordstrom"
        },
        {
            "id": 8479547,
            "name": "Matthew Phillips"
        },
        {
            "id": 8474736,
            "name": "Zac Rinaldo"
        },
        {
            "id": 8476439,
            "name": "Brett Ritchie"
        },
        {
            "id": 8477210,
            "name": "Buddy Robinson"
        },
        {
            "id": 8480008,
            "name": "Adam Ruzicka"
        },
        {
            "id": 8478585,
            "name": "Derek Ryan"
        },
        {
            "id": 8478866,
            "name": "Dominik Simon"
        },
        {
            "id": 8479314,
            "name": "Matthew Tkachuk"
        },
        {
            "id": 8478397,
            "name": "Rasmus Andersson"
        },
        {
            "id": 8470966,
            "name": "Mark Giordano"
        },
        {
            "id": 8478396,
            "name": "Noah Hanifin"
        },
        {
            "id": 8478430,
            "name": "Oliver Kylington"
        },
        {
            "id": 8482067,
            "name": "Connor Mackey"
        },
        {
            "id": 8476300,
            "name": "Nikita Nesterov"
        },
        {
            "id": 8474628,
            "name": "Michael Stone"
        },
        {
            "id": 8475690,
            "name": "Chris Tanev"
        },
        {
            "id": 8479976,
            "name": "Juuso V\u00e4lim\u00e4ki"
        },
        {
            "id": 8475839,
            "name": "Louis Domingue"
        },
        {
            "id": 8474593,
            "name": "Jacob Markstrom"
        },
        {
            "id": 8479496,
            "name": "David Rittich"
        },
        {
            "id": 8481501,
            "name": "Artyom Zagidulin"
        }
    ]
}