{
    "players": [
        {
            "id": 8445022,
            "name": "Syl Apps"
        },
        {
            "id": 8445460,
            "name": "Wayne Bianchin"
        },
        {
            "id": 8445332,
            "name": "Gene Carr"
        },
        {
            "id": 8445350,
            "name": "Tom Cassidy"
        },
        {
            "id": 8446035,
            "name": "Blair Chapman"
        },
        {
            "id": 8445614,
            "name": "Mike Corrigan"
        },
        {
            "id": 8446170,
            "name": "Jacques Cossette"
        },
        {
            "id": 8446320,
            "name": "Kim Davis"
        },
        {
            "id": 8446849,
            "name": "John Flesch"
        },
        {
            "id": 8447492,
            "name": "Jim Hamilton"
        },
        {
            "id": 8448420,
            "name": "Rick Kehoe"
        },
        {
            "id": 8448707,
            "name": "Pierre Larouche"
        },
        {
            "id": 8448741,
            "name": "Peter Lee"
        },
        {
            "id": 8447536,
            "name": "Lowell MacDonald"
        },
        {
            "id": 8449062,
            "name": "Peter Mahovlich"
        },
        {
            "id": 8449101,
            "name": "Greg Malone"
        },
        {
            "id": 8449675,
            "name": "Hartland Monahan"
        },
        {
            "id": 8447897,
            "name": "Lew Morrison"
        },
        {
            "id": 8450566,
            "name": "Jean Pronovost"
        },
        {
            "id": 8448671,
            "name": "Derek Sanderson"
        },
        {
            "id": 8451245,
            "name": "Dave Schultz"
        },
        {
            "id": 8451614,
            "name": "Brian Spencer"
        },
        {
            "id": 8444961,
            "name": "Russ Anderson"
        },
        {
            "id": 8445792,
            "name": "Dave Burrows"
        },
        {
            "id": 8445893,
            "name": "Colin Campbell"
        },
        {
            "id": 8446593,
            "name": "Tom Edur"
        },
        {
            "id": 8446780,
            "name": "Mario Faubert"
        },
        {
            "id": 8450085,
            "name": "Dennis Owchar"
        },
        {
            "id": 8450168,
            "name": "Bob Paradise"
        },
        {
            "id": 8450555,
            "name": "Thomas Price"
        },
        {
            "id": 8451624,
            "name": "Ron Stackhouse"
        },
        {
            "id": 8447755,
            "name": "Denis Herron"
        },
        {
            "id": 8448710,
            "name": "Gordon Laxton"
        },
        {
            "id": 8450097,
            "name": "Greg Redquest"
        },
        {
            "id": 8450148,
            "name": "Dunc Wilson"
        }
    ]
}