{
    "players": [
        {
            "id": 8444912,
            "name": "Steve Alley"
        },
        {
            "id": 8444913,
            "name": "Ray Allison"
        },
        {
            "id": 8445015,
            "name": "Mike Antonovich"
        },
        {
            "id": 8445414,
            "name": "Bill Bennett"
        },
        {
            "id": 8445618,
            "name": "Pat Boutette"
        },
        {
            "id": 8445723,
            "name": "Jeff Brubaker"
        },
        {
            "id": 8445981,
            "name": "Greg Carroll"
        },
        {
            "id": 8446355,
            "name": "Dave Debol"
        },
        {
            "id": 8446469,
            "name": "Jordy Douglas"
        },
        {
            "id": 8446940,
            "name": "Nick Fotiu"
        },
        {
            "id": 8447508,
            "name": "Al Hangsleben"
        },
        {
            "id": 8447821,
            "name": "Brian Hill"
        },
        {
            "id": 8448000,
            "name": "Gordie Howe"
        },
        {
            "id": 8448108,
            "name": "Bobby Hull"
        },
        {
            "id": 8448327,
            "name": "Bernie Johnston"
        },
        {
            "id": 8448468,
            "name": "Dave Keon"
        },
        {
            "id": 8448612,
            "name": "Andre Lacroix"
        },
        {
            "id": 8449860,
            "name": "Ray Neufeld"
        },
        {
            "id": 8450981,
            "name": "Mike Rogers"
        },
        {
            "id": 8451028,
            "name": "Tom Rowe"
        },
        {
            "id": 8451145,
            "name": "Jean Savard"
        },
        {
            "id": 8451244,
            "name": "Maynard Schurman"
        },
        {
            "id": 8451324,
            "name": "Timothy Sheehy"
        },
        {
            "id": 8451696,
            "name": "Robert Stephenson"
        },
        {
            "id": 8451770,
            "name": "Blaine Stoughton"
        },
        {
            "id": 8452294,
            "name": "James Warner"
        },
        {
            "id": 8447209,
            "name": "Larry Giroux"
        },
        {
            "id": 8447911,
            "name": "Rick Hodgson"
        },
        {
            "id": 8448002,
            "name": "Mark Howe"
        },
        {
            "id": 8448005,
            "name": "Marty Howe"
        },
        {
            "id": 8448838,
            "name": "Rick Ley"
        },
        {
            "id": 8448906,
            "name": "Charles Luksa"
        },
        {
            "id": 8450478,
            "name": "Ronald Plumb"
        },
        {
            "id": 8450798,
            "name": "Mark Renaud"
        },
        {
            "id": 8450905,
            "name": "Gordie Roberts"
        },
        {
            "id": 8451364,
            "name": "Al Sims"
        },
        {
            "id": 8451561,
            "name": "Stuart Smith"
        },
        {
            "id": 8447066,
            "name": "John Garrett"
        },
        {
            "id": 8451474,
            "name": "Al Smith"
        }
    ]
}