{
    "players": [
        {
            "id": 8444897,
            "name": "Keith Acton"
        },
        {
            "id": 8445054,
            "name": "Jim Archibald"
        },
        {
            "id": 8445417,
            "name": "Brian Bellows"
        },
        {
            "id": 8445492,
            "name": "Scott Bjugstad"
        },
        {
            "id": 8445690,
            "name": "Bob Brooke"
        },
        {
            "id": 8445724,
            "name": "Neal Broten"
        },
        {
            "id": 8445932,
            "name": "Jack Carlson"
        },
        {
            "id": 8446063,
            "name": "Dino Ciccarelli"
        },
        {
            "id": 8446356,
            "name": "Larry Depalma"
        },
        {
            "id": 8447345,
            "name": "Dirk Graham"
        },
        {
            "id": 8447440,
            "name": "Marc Habscheid"
        },
        {
            "id": 8447479,
            "name": "Mats Hallin"
        },
        {
            "id": 8447732,
            "name": "Raimo Helminen"
        },
        {
            "id": 8447975,
            "name": "Paul Houck"
        },
        {
            "id": 8448689,
            "name": "Brian Lawton"
        },
        {
            "id": 8448980,
            "name": "Brian MacLellan"
        },
        {
            "id": 8449284,
            "name": "Dennis Maruk"
        },
        {
            "id": 8449445,
            "name": "Tony McKegney"
        },
        {
            "id": 8449887,
            "name": "Kent Nilsson"
        },
        {
            "id": 8450251,
            "name": "Mark Pavelich"
        },
        {
            "id": 8450259,
            "name": "Steve Payne"
        },
        {
            "id": 8450474,
            "name": "Willi Plett"
        },
        {
            "id": 8451535,
            "name": "Randy Smith"
        },
        {
            "id": 8451926,
            "name": "Sean Toomey"
        },
        {
            "id": 8445625,
            "name": "Paul Boutilier"
        },
        {
            "id": 8446045,
            "name": "Colin Chisholm"
        },
        {
            "id": 8447176,
            "name": "Curt Giles"
        },
        {
            "id": 8447436,
            "name": "Jari Gronstrand"
        },
        {
            "id": 8447667,
            "name": "Craig Hartsburg"
        },
        {
            "id": 8449315,
            "name": "Brad Maxwell"
        },
        {
            "id": 8446955,
            "name": "Frantisek Musil"
        },
        {
            "id": 8450558,
            "name": "Christopher Pryor"
        },
        {
            "id": 8450905,
            "name": "Gordie Roberts"
        },
        {
            "id": 8451022,
            "name": "Bob Rouse"
        },
        {
            "id": 8452227,
            "name": "Emanuel Viveiros"
        },
        {
            "id": 8452484,
            "name": "Ron Wilson"
        },
        {
            "id": 8445381,
            "name": "Don Beaupre"
        },
        {
            "id": 8451121,
            "name": "Michael Sands"
        },
        {
            "id": 8451845,
            "name": "Kari Takko"
        }
    ]
}