{
    "players": [
        {
            "id": 8451820,
            "name": "Bob Sweeney"
        },
        {
            "id": 8450270,
            "name": "Allen Pedersen"
        },
        {
            "id": 8445729,
            "name": "Paul Brydges"
        },
        {
            "id": 8447673,
            "name": "Mike Hartman"
        },
        {
            "id": 8448821,
            "name": "Robert Logan"
        },
        {
            "id": 8450199,
            "name": "Jeff Parker"
        },
        {
            "id": 8450560,
            "name": "Ken Priestlay"
        },
        {
            "id": 8451080,
            "name": "Christian Ruuttu"
        },
        {
            "id": 8451940,
            "name": "Doug Trapp"
        },
        {
            "id": 8444957,
            "name": "Shawn Anderson"
        },
        {
            "id": 8446792,
            "name": "Mark Ferner"
        },
        {
            "id": 8448554,
            "name": "Uwe Krupp"
        },
        {
            "id": 8449893,
            "name": "Joe Nieuwendyk"
        },
        {
            "id": 8450900,
            "name": "Gary Roberts"
        },
        {
            "id": 8447437,
            "name": "Kevan Guy"
        },
        {
            "id": 8446294,
            "name": "Doug Dadswell"
        },
        {
            "id": 8451117,
            "name": "Everett Sanipass"
        },
        {
            "id": 8451163,
            "name": "Darin Sceviour"
        },
        {
            "id": 8451673,
            "name": "Mike Stapleton"
        },
        {
            "id": 8452226,
            "name": "Dan Vincelette"
        },
        {
            "id": 8449123,
            "name": "Dave Manson"
        },
        {
            "id": 8448541,
            "name": "Dale Krentz"
        },
        {
            "id": 8449751,
            "name": "Joe Murphy"
        },
        {
            "id": 8446051,
            "name": "Steve Chiasson"
        },
        {
            "id": 8451329,
            "name": "Jeff Sharples"
        },
        {
            "id": 8445733,
            "name": "Kelly Buchberger"
        },
        {
            "id": 8452159,
            "name": "Wayne Van Dorp"
        },
        {
            "id": 8446071,
            "name": "Shane Churla"
        },
        {
            "id": 8449610,
            "name": "Mike Millar"
        },
        {
            "id": 8445979,
            "name": "Jimmy Carson"
        },
        {
            "id": 8450941,
            "name": "Luc Robitaille"
        },
        {
            "id": 8446418,
            "name": "Peter Dineen"
        },
        {
            "id": 8446494,
            "name": "Steve Duchesne"
        },
        {
            "id": 8451926,
            "name": "Sean Toomey"
        },
        {
            "id": 8446045,
            "name": "Colin Chisholm"
        },
        {
            "id": 8447436,
            "name": "Jari Gronstrand"
        },
        {
            "id": 8446955,
            "name": "Frantisek Musil"
        },
        {
            "id": 8451915,
            "name": "Gilles Thibaudeau"
        },
        {
            "id": 8451116,
            "name": "Scott Sandelin"
        },
        {
            "id": 8445730,
            "name": "Doug Brown"
        },
        {
            "id": 8445937,
            "name": "Anders Carlsson"
        },
        {
            "id": 8448799,
            "name": "Tim Lenardon"
        },
        {
            "id": 8449167,
            "name": "Gordon Mark"
        },
        {
            "id": 8446971,
            "name": "Karl Friesen"
        },
        {
            "id": 8451860,
            "name": "Chris Terreri"
        },
        {
            "id": 8448489,
            "name": "Derek King"
        },
        {
            "id": 8448664,
            "name": "Brad Lauer"
        },
        {
            "id": 8452501,
            "name": "Randy Wood"
        },
        {
            "id": 8446013,
            "name": "Jay Caufield"
        },
        {
            "id": 8446449,
            "name": "Mike Donnelly"
        },
        {
            "id": 8451844,
            "name": "Ron Talakoski"
        },
        {
            "id": 8452252,
            "name": "Gord Walker"
        },
        {
            "id": 8445920,
            "name": "Terry Carkner"
        },
        {
            "id": 8448961,
            "name": "Norm MacIver"
        },
        {
            "id": 8445440,
            "name": "Craig Berube"
        },
        {
            "id": 8446450,
            "name": "Brian Dobbin"
        },
        {
            "id": 8446970,
            "name": "Mark Freer"
        },
        {
            "id": 8451260,
            "name": "Glen Seabrooke"
        },
        {
            "id": 8446050,
            "name": "Jeff Chychrun"
        },
        {
            "id": 8448048,
            "name": "Kerry Huffman"
        },
        {
            "id": 8451570,
            "name": "Greg Smyth"
        },
        {
            "id": 8451710,
            "name": "John Stevens"
        },
        {
            "id": 8447775,
            "name": "Ron Hextall"
        },
        {
            "id": 8447165,
            "name": "Lee Giffin"
        },
        {
            "id": 8447390,
            "name": "Steve Guenette"
        },
        {
            "id": 8447754,
            "name": "Yves Heroux"
        },
        {
            "id": 8448627,
            "name": "Jason Lafreniere"
        },
        {
            "id": 8449589,
            "name": "Max Middendorf"
        },
        {
            "id": 8450611,
            "name": "Ken Quinney"
        },
        {
            "id": 8451330,
            "name": "Scott Shaunessy"
        },
        {
            "id": 8452687,
            "name": "Richard Zemlak"
        },
        {
            "id": 8446733,
            "name": "Todd Ewen"
        },
        {
            "id": 8448017,
            "name": "Tony Hrkac"
        },
        {
            "id": 8448781,
            "name": "Jocelyn Lemieux"
        },
        {
            "id": 8446315,
            "name": "Michael Dark"
        },
        {
            "id": 8446303,
            "name": "Vincent Damphousse"
        },
        {
            "id": 8446782,
            "name": "Ted Fauss"
        },
        {
            "id": 8449037,
            "name": "Kevin Maguire"
        },
        {
            "id": 8448765,
            "name": "John Leblanc"
        },
        {
            "id": 8444893,
            "name": "Jim Agnew"
        },
        {
            "id": 8447029,
            "name": "Troy Gamble"
        },
        {
            "id": 8445223,
            "name": "Joel Baillargeon"
        },
        {
            "id": 8446516,
            "name": "Iain Duncan"
        },
        {
            "id": 8446682,
            "name": "Craig Endean"
        },
        {
            "id": 8448253,
            "name": "Hannu Jarvenpaa"
        },
        {
            "id": 8448366,
            "name": "Brad Jones"
        },
        {
            "id": 8449971,
            "name": "Fredrik Olausson"
        },
        {
            "id": 8450727,
            "name": "Eldon Reddick"
        },
        {
            "id": 8447391,
            "name": "Jeff Greenlaw"
        },
        {
            "id": 8450408,
            "name": "Michal Pivonka"
        },
        {
            "id": 8451914,
            "name": "Jim Thomson"
        },
        {
            "id": 8446014,
            "name": "Paul Cavallini"
        }
    ]
}